b21scripts/__init__.py
b21scripts/readwrite/__init__.py
b21scripts/readwrite/dat.py
b21scripts/readwrite/interface.py
b21scripts/readwrite/pdb.py
b21scripts/saxs/__init__.py
b21scripts/saxs/saxs_calc.py
b21scripts-1.1.1.dist-info/LICENCE
b21scripts-1.1.1.dist-info/METADATA
b21scripts-1.1.1.dist-info/WHEEL
b21scripts-1.1.1.dist-info/top_level.txt
b21scripts-1.1.1.dist-info/RECORD
