Metadata-Version: 2.1
Name: b21scripts
Version: 1.1.1
Summary: Libraries for SAXS data manipulation and analysis
Home-page: https://github.com/nathancowieson/b21scripts.git
Author: Nathan Cowieson
Author-email: nathan.cowieson@diamond.ac.uk
Project-URL: Bug Tracker, https://github.com/pypa/b21scripts/issues
Classifier: Programming Language :: Python :: 3
Classifier: License :: OSI Approved :: MIT License
Classifier: Operating System :: OS Independent
Requires-Python: >=3.6
License-File: LICENCE
Requires-Dist: numpy
Requires-Dist: matplotlib
